shims/__init__.py
shims/core.py
shims/pytestplugin.py
shims-0.0.1.dist-info/METADATA
shims-0.0.1.dist-info/WHEEL
shims-0.0.1.dist-info/entry_points.txt
shims-0.0.1.dist-info/top_level.txt
shims-0.0.1.dist-info/RECORD
