Metadata-Version: 2.1
Name: shims
Version: 0.0.1
Summary: Patching and mocking utilities
Home-page: http://www.grantjenks.com/docs/shims/
Author: Grant Jenks
Author-email: contact@grantjenks.com
License: Apache 2.0
Platform: UNKNOWN
Classifier: Development Status :: 3 - Alpha
Classifier: Intended Audience :: Developers
Classifier: License :: OSI Approved :: Apache Software License
Classifier: Natural Language :: English
Classifier: Programming Language :: Python
Classifier: Programming Language :: Python :: 3
Classifier: Programming Language :: Python :: 3.6
Classifier: Programming Language :: Python :: 3.7
Classifier: Programming Language :: Python :: 3.8
Classifier: Programming Language :: Python :: Implementation :: CPython
Requires-Dist: pytest
